stacked_quantile/__init__.py
stacked_quantile/main.py
stacked_quantile/py.typed
stacked_quantile/typed_np_functions.py
stacked_quantile-0.4.0.dist-info/METADATA
stacked_quantile-0.4.0.dist-info/WHEEL
stacked_quantile-0.4.0.dist-info/top_level.txt
stacked_quantile-0.4.0.dist-info/RECORD
