Metadata-Version: 2.1
Name: stacked_quantile
Version: 0.4.0
Summary: Get weighted median values, treating weights as the number of occurrences of a given value.
Author-email: Shay Hill <shay_public@hotmail.com>
License: MIT
Requires-Python: >=3.9
Requires-Dist: numpy
Provides-Extra: dev
Requires-Dist: commitizen ; extra == 'dev'
Requires-Dist: pre-commit ; extra == 'dev'
Requires-Dist: pytest ; extra == 'dev'
Requires-Dist: tox ; extra == 'dev'
